nextline/__about__.py
nextline/__init__.py
nextline/continuous.py
nextline/count.py
nextline/disable.py
nextline/events.py
nextline/imp.py
nextline/main.py
nextline/py.typed
nextline/types.py
nextline/fsm/__init__.py
nextline/fsm/callback.py
nextline/fsm/config.py
nextline/fsm/machine.py
nextline/plugin/__init__.py
nextline/plugin/hook.py
nextline/plugin/spec.py
nextline/plugin/plugins/__init__.py
nextline/plugin/plugins/argument.py
nextline/plugin/plugins/registrars/__init__.py
nextline/plugin/plugins/registrars/prompt_info.py
nextline/plugin/plugins/registrars/prompt_notice.py
nextline/plugin/plugins/registrars/run_info.py
nextline/plugin/plugins/registrars/run_no.py
nextline/plugin/plugins/registrars/script.py
nextline/plugin/plugins/registrars/state_name.py
nextline/plugin/plugins/registrars/stdout.py
nextline/plugin/plugins/registrars/trace_info.py
nextline/plugin/plugins/registrars/trace_nos.py
nextline/plugin/plugins/session/__init__.py
nextline/plugin/plugins/session/monitor.py
nextline/plugin/plugins/session/session.py
nextline/spawned/__init__.py
nextline/spawned/call.py
nextline/spawned/commands.py
nextline/spawned/exc.py
nextline/spawned/path.py
nextline/spawned/runner.py
nextline/spawned/types.py
nextline/spawned/utils.py
nextline/spawned/plugin/__init__.py
nextline/spawned/plugin/hook.py
nextline/spawned/plugin/skip.py
nextline/spawned/plugin/spec.py
nextline/spawned/plugin/plugins/__init__.py
nextline/spawned/plugin/plugins/_script.py
nextline/spawned/plugin/plugins/compose.py
nextline/spawned/plugin/plugins/concurrency.py
nextline/spawned/plugin/plugins/filter.py
nextline/spawned/plugin/plugins/global_.py
nextline/spawned/plugin/plugins/local_.py
nextline/spawned/plugin/plugins/peek.py
nextline/spawned/plugin/plugins/repeat.py
nextline/spawned/plugin/plugins/pdb_/__init__.py
nextline/spawned/plugin/plugins/pdb_/custom.py
nextline/spawned/plugin/plugins/pdb_/factory.py
nextline/spawned/plugin/plugins/pdb_/prompt.py
nextline-0.7.21.dist-info/METADATA
nextline-0.7.21.dist-info/WHEEL
nextline-0.7.21.dist-info/licenses/LICENSE
nextline-0.7.21.dist-info/RECORD
