Metadata-Version: 2.4
Name: nextline
Version: 0.7.21
Summary: A Python library for controlling Python scripts execution
Project-URL: Homepage, https://github.com/simonsobs/nextline#readme
Project-URL: Issues, https://github.com/simonsobs/nextline/issues
Project-URL: Source, https://github.com/simonsobs/nextline
Author-email: Simons Observatory <so_software@simonsobservatory.org>
License-Expression: MIT
License-File: LICENSE
Classifier: Development Status :: 4 - Beta
Classifier: Intended Audience :: Science/Research
Classifier: License :: OSI Approved :: MIT License
Classifier: Programming Language :: Python
Classifier: Programming Language :: Python :: 3.10
Classifier: Programming Language :: Python :: 3.11
Classifier: Programming Language :: Python :: 3.12
Classifier: Programming Language :: Python :: 3.13
Classifier: Programming Language :: Python :: 3.14
Requires-Python: >=3.10
Requires-Dist: apluggy>=1.0
Requires-Dist: exceptiongroup>=1.2
Requires-Dist: transitions>=0.9.0
Provides-Extra: dev
Requires-Dist: mypy; extra == 'dev'
Requires-Dist: tox; extra == 'dev'
Requires-Dist: twine; extra == 'dev'
Provides-Extra: tests
Requires-Dist: hypothesis>=6.117; extra == 'tests'
Requires-Dist: nextline-test-utils>=0.1; extra == 'tests'
Requires-Dist: pytest-asyncio>=0.18; extra == 'tests'
Requires-Dist: pytest-cov>=4.0; extra == 'tests'
Requires-Dist: pytest-timeout>=2.1; extra == 'tests'
Requires-Dist: pytest>=8.0; extra == 'tests'
